business_models_initial/__init__.py
business_models_initial/chi_performance.py
business_models_initial/chi_performance_parsed_table.py
business_models_initial-0.0.2.dist-info/LICENSE.txt
business_models_initial-0.0.2.dist-info/METADATA
business_models_initial-0.0.2.dist-info/WHEEL
business_models_initial-0.0.2.dist-info/top_level.txt
business_models_initial-0.0.2.dist-info/RECORD
